agilequant_my_project/__init__.py
agilequant_my_project/test
agilequant_my_project-0.1.0.dist-info/WHEEL
agilequant_my_project-0.1.0.dist-info/entry_points.txt
agilequant_my_project-0.1.0.dist-info/METADATA
agilequant_my_project-0.1.0.dist-info/RECORD
