Metadata-Version: 2.3
Name: agilequant-my-project
Version: 0.1.0
Summary: Add your description here
Author: agilequant
Author-email: agilequant <quantinvestment@163.com>
Requires-Dist: ruff>=0.13.1
Requires-Python: >=3.10
